pfstools/__init__.py
pfstools/output.py
pfstools/sql.py
pfstools/tools.py
pfstools-0.2.4.dist-info/METADATA
pfstools-0.2.4.dist-info/WHEEL
pfstools-0.2.4.dist-info/licenses/LICENSE
pfstools-0.2.4.dist-info/RECORD
