Metadata-Version: 2.1
Name: pfstools
Version: 0.2.4
Summary: Tools for my regular use. Particular to my work environment: SQL Server with Windows authentication
Project-URL: Homepage, https://github.com/jakeb/pfs-data-tools
Project-URL: Bug Tracker, https://github.com/jakeb/pfs-data-tools/issues
Author-email: Jake Bridge <bridge.jake@gmail.com>
License-File: LICENSE
Classifier: License :: OSI Approved :: MIT License
Classifier: Operating System :: OS Independent
Classifier: Programming Language :: Python :: 3
Requires-Python: >=3.7
Requires-Dist: openpyxl
Requires-Dist: pandas
Requires-Dist: pyodbc
Requires-Dist: python-dotenv
Requires-Dist: sqlalchemy
Requires-Dist: xlsxwriter
